{
  "project_info": {
    "project_number": "498356049581",
    "project_id": "jet10app",
    "storage_bucket": "jet10app.firebasestorage.app"
  },
  "client": [
    {
      "client_info": {
        "mobilesdk_app_id": "1:498356049581:android:25c5bc1993dbf2b0e7d824",
        "android_client_info": {
          "package_name": "com.example.jet10"
        }
      },
      "oauth_client": [],
      "api_key": [
        {
          "current_key": "AIzaSyALX5F3msktM2clkhqJQxIWtlyLE-GJj6I"
        }
      ],
      "services": {
        "appinvite_service": {
          "other_platform_oauth_client": []
        }
      }
    }
  ],
  "configuration_version": "1"
}